MANIFEST.in
README.rst
pyproject.toml
requirements.txt
setup.py
blob_utils/__init__.py
blob_utils/blob_host.py
blob_utils/blob_host_factory.py
blob_utils/dspace_blob_host.py
blob_utils/gridfs_blob_host.py
blob_utils.egg-info/PKG-INFO
blob_utils.egg-info/SOURCES.txt
blob_utils.egg-info/dependency_links.txt
blob_utils.egg-info/requires.txt
blob_utils.egg-info/top_level.txt
blob_utils/commons/__init__.py
blob_utils/commons/exceptions.py
tests/__init__.py
tests/test_settings.py
tests/gridfs_blob_host/__init__.py
tests/gridfs_blob_host/tests_int.py