Metadata-Version: 1.0
Name: blob-utils
Version: 1.14.0
Summary: File management utils for the curator core project
Home-page: https://github.com/usnistgov/blob_utils
Author: NIST IT Lab
Author-email: itl_inquiries@nist.gov
License: UNKNOWN
Platform: UNKNOWN
